Metadata-Version: 1.1
Name: dumbelek
Version: 2.1.3
Summary: Text processing library for languages Turkish and English
Home-page: https://github.com/taylangezici/dumbelek
Author: Taylan Gezici
Author-email: taylangezici@gmail.com
License: MIT
Download-URL: https://github.com/taylangezici/dumbelek/archive/refs/tags/v2.1.3.tar.gz
Keywords: none
Platform: UNKNOWN
Classifier: Development Status :: 3 - Alpha
Classifier: Intended Audience :: Developers
Classifier: Topic :: Software Development :: Build Tools
Classifier: License :: OSI Approved :: MIT License
Classifier: Programming Language :: Python :: 3
Classifier: Programming Language :: Python :: 3.4
Classifier: Programming Language :: Python :: 3.5
Classifier: Programming Language :: Python :: 3.6
